lhcbdiracx/logic/__init__.py
lhcbdiracx/logic/py.typed
lhcbdiracx/logic/bookkeeping/__init__.py
lhcbdiracx/logic/bookkeeping/bookkeeping.py
lhcbdiracx_logic-0.0.7.dist-info/METADATA
lhcbdiracx_logic-0.0.7.dist-info/WHEEL
lhcbdiracx_logic-0.0.7.dist-info/top_level.txt
lhcbdiracx_logic-0.0.7.dist-info/RECORD
