Metadata-Version: 2.4
Name: lhcbdiracx-logic
Version: 0.0.7
Summary: TODO
License: GPL-3.0-only
Classifier: Intended Audience :: Science/Research
Classifier: License :: OSI Approved :: GNU General Public License v3 (GPLv3)
Classifier: Programming Language :: Python :: 3
Classifier: Topic :: Scientific/Engineering
Classifier: Topic :: System :: Distributed Computing
Requires-Python: >=3.11
Requires-Dist: lhcbdiracx-core
Requires-Dist: lhcbdiracx-db
Requires-Dist: diracx-logic==0.0.7
Provides-Extra: types
Requires-Dist: diracx-logic[testing]==0.0.7; extra == "types"
Requires-Dist: boto3-stubs; extra == "types"
Requires-Dist: types-aiobotocore[essential]; extra == "types"
Requires-Dist: types-aiobotocore-s3; extra == "types"
Requires-Dist: types-cachetools; extra == "types"
Requires-Dist: types-python-dateutil; extra == "types"
Requires-Dist: types-PyYAML; extra == "types"
Requires-Dist: types-requests; extra == "types"
Provides-Extra: testing
Requires-Dist: diracx-api[testing]==0.0.7; extra == "testing"
